rapidframework/__init__.py
rapidframework/config.py
rapidframework/main.py
rapidframework/template.py
rapidframework/__pycache__/main.cpython-313.pyc
rapidframework/configs/managers.json
rapidframework/frameworks/__init__.py
rapidframework/frameworks/django.py
rapidframework/frameworks/fastapi.py
rapidframework/frameworks/simple_frameworks.py
rapidframework/frameworks/examples/__init__.py
rapidframework/frameworks/examples/bottle_1.py
rapidframework/frameworks/examples/cherrypy_1.py
rapidframework/frameworks/examples/fastapi_1.py
rapidframework/frameworks/examples/flask_1.py
rapidframework/frameworks/examples/grok_1.py
rapidframework/frameworks/examples/litestar_1.py
rapidframework/frameworks/examples/pyramid_1.py
rapidframework/frameworks/examples/socketify_1.py
rapidframework/frameworks/examples/starlette_1.py
rapidframework/frameworks/examples/tornado_1.py
rapidframework/frameworks/examples/turbogears2_1.py
rapidframework/frameworks/examples/web2py_1.py
rapidframework/frameworks/examples/django_1/manage.py-tpl
rapidframework/frameworks/examples/django_1/project_name/__init__.py-tpl
rapidframework/frameworks/examples/django_1/project_name/asgi.py-tpl
rapidframework/frameworks/examples/django_1/project_name/settings.py-tpl
rapidframework/frameworks/examples/django_1/project_name/urls.py-tpl
rapidframework/frameworks/examples/django_1/project_name/wsgi.py-tpl
rapidframework/frameworks/examples/django_1/project_name/users/__init__.py-tpl
rapidframework/frameworks/examples/django_1/project_name/users/admin.py-tpl
rapidframework/frameworks/examples/django_1/project_name/users/models.py-tpl
rapidframework/frameworks/examples/django_1/project_name/users/migrations/0001_initial.py-tpl
rapidframework/frameworks/examples/django_1/project_name/users/migrations/__init__.py-tpl
rapidframework_lib-1.1.1.dist-info/licenses/LICENSE
rapidframework_lib-1.1.1.dist-info/METADATA
rapidframework_lib-1.1.1.dist-info/WHEEL
rapidframework_lib-1.1.1.dist-info/entry_points.txt
rapidframework_lib-1.1.1.dist-info/top_level.txt
rapidframework_lib-1.1.1.dist-info/RECORD
