Metadata-Version: 2.4
Name: rapidframework-lib
Version: 1.1.1
License-File: LICENSE
Requires-Dist: msgspec
Dynamic: description
Dynamic: description-content-type
Dynamic: license-file
Dynamic: requires-dist
